<?xml version="1.0" encoding="UTF-8"?>
<!DOCTYPE mapper PUBLIC "-//mybatis.org//DTD Mapper 3.0//EN" "http://mybatis.org/dtd/mybatis-3-mapper.dtd">
<mapper namespace="com.realc.safe.mapper.LevelUserMapper">
  <resultMap id="BaseResultMap" type="com.realc.safe.model.LevelUser">
    <!--
      WARNING - @mbg.generated
      This element is automatically generated by MyBatis Generator, do not modify.
    -->
    <id column="level_user_id" jdbcType="VARCHAR" property="levelUserId" />
    <result column="level_user_value" jdbcType="INTEGER" property="levelUserValue" />
    <result column="level_user_name" jdbcType="VARCHAR" property="levelUserName" />
    <result column="create_time" jdbcType="VARCHAR" property="createTime" />
    <result column="level_user_points" jdbcType="INTEGER" property="levelUserPoints" />
    <result column="level_user_percent" jdbcType="TINYINT" property="levelUserPercent" />
  </resultMap>
  <sql id="Base_Column_List">
    <!--
      WARNING - @mbg.generated
      This element is automatically generated by MyBatis Generator, do not modify.
    -->
    level_user_id, level_user_value, level_user_name, create_time, level_user_points, 
    level_user_percent
  </sql>
  <select id="selectByPrimaryKey" parameterType="java.lang.String" resultMap="BaseResultMap">
    <!--
      WARNING - @mbg.generated
      This element is automatically generated by MyBatis Generator, do not modify.
    -->
    select 
    <include refid="Base_Column_List" />
    from realc_level_user
    where level_user_id = #{levelUserId,jdbcType=VARCHAR}
  </select>
  <delete id="deleteByPrimaryKey" parameterType="java.lang.String">
    <!--
      WARNING - @mbg.generated
      This element is automatically generated by MyBatis Generator, do not modify.
    -->
    delete from realc_level_user
    where level_user_id = #{levelUserId,jdbcType=VARCHAR}
  </delete>
  <insert id="insert" parameterType="com.realc.safe.model.LevelUser">
    <!--
      WARNING - @mbg.generated
      This element is automatically generated by MyBatis Generator, do not modify.
    -->
    insert into realc_level_user (level_user_id, level_user_value, level_user_name, 
      create_time, level_user_points, level_user_percent
      )
    values (#{levelUserId,jdbcType=VARCHAR}, #{levelUserValue,jdbcType=INTEGER}, #{levelUserName,jdbcType=VARCHAR}, 
      #{createTime,jdbcType=VARCHAR}, #{levelUserPoints,jdbcType=INTEGER}, #{levelUserPercent,jdbcType=TINYINT}
      )
  </insert>
  <insert id="insertSelective" parameterType="com.realc.safe.model.LevelUser">
    <!--
      WARNING - @mbg.generated
      This element is automatically generated by MyBatis Generator, do not modify.
    -->
    insert into realc_level_user
    <trim prefix="(" suffix=")" suffixOverrides=",">
      <if test="levelUserId != null">
        level_user_id,
      </if>
      <if test="levelUserValue != null">
        level_user_value,
      </if>
      <if test="levelUserName != null">
        level_user_name,
      </if>
      <if test="createTime != null">
        create_time,
      </if>
      <if test="levelUserPoints != null">
        level_user_points,
      </if>
      <if test="levelUserPercent != null">
        level_user_percent,
      </if>
    </trim>
    <trim prefix="values (" suffix=")" suffixOverrides=",">
      <if test="levelUserId != null">
        #{levelUserId,jdbcType=VARCHAR},
      </if>
      <if test="levelUserValue != null">
        #{levelUserValue,jdbcType=INTEGER},
      </if>
      <if test="levelUserName != null">
        #{levelUserName,jdbcType=VARCHAR},
      </if>
      <if test="createTime != null">
        #{createTime,jdbcType=VARCHAR},
      </if>
      <if test="levelUserPoints != null">
        #{levelUserPoints,jdbcType=INTEGER},
      </if>
      <if test="levelUserPercent != null">
        #{levelUserPercent,jdbcType=TINYINT},
      </if>
    </trim>
  </insert>
  <update id="updateByPrimaryKeySelective" parameterType="com.realc.safe.model.LevelUser">
    <!--
      WARNING - @mbg.generated
      This element is automatically generated by MyBatis Generator, do not modify.
    -->
    update realc_level_user
    <set>
      <if test="levelUserValue != null">
        level_user_value = #{levelUserValue,jdbcType=INTEGER},
      </if>
      <if test="levelUserName != null">
        level_user_name = #{levelUserName,jdbcType=VARCHAR},
      </if>
      <if test="createTime != null">
        create_time = #{createTime,jdbcType=VARCHAR},
      </if>
      <if test="levelUserPoints != null">
        level_user_points = #{levelUserPoints,jdbcType=INTEGER},
      </if>
      <if test="levelUserPercent != null">
        level_user_percent = #{levelUserPercent,jdbcType=TINYINT},
      </if>
    </set>
    where level_user_id = #{levelUserId,jdbcType=VARCHAR}
  </update>
  <update id="updateByPrimaryKey" parameterType="com.realc.safe.model.LevelUser">
    <!--
      WARNING - @mbg.generated
      This element is automatically generated by MyBatis Generator, do not modify.
    -->
    update realc_level_user
    set level_user_value = #{levelUserValue,jdbcType=INTEGER},
      level_user_name = #{levelUserName,jdbcType=VARCHAR},
      create_time = #{createTime,jdbcType=VARCHAR},
      level_user_points = #{levelUserPoints,jdbcType=INTEGER},
      level_user_percent = #{levelUserPercent,jdbcType=TINYINT}
    where level_user_id = #{levelUserId,jdbcType=VARCHAR}
  </update>
</mapper>